[
  {
    "id": "1",
    "name": "소설"
  },
  {
    "id": "2",
    "name": "시/에세이"
  },
  {
    "id": "3",
    "name": "인문학"
  },
  {
    "id": "4",
    "name": "경제/경영"
  },
  {
    "id": "5",
    "name": "자기계발"
  },
  {
    "id": "6",
    "name": "정치/사회"
  },
  {
    "id": "7",
    "name": "역사/문화"
  },
  {
    "id": "8",
    "name": "종교"
  },
  {
    "id": "9",
    "name": "외국어"
  },
  {
    "id": "10",
    "name": "여행"
  },
  {
    "id": "11",
    "name": "건강"
  },
  {
    "id": "12",
    "name": "요리"
  }
]
